medium_multiply_test/__init__.py
medium_multiply_test/multiplication.py
medium_multiply_test/with_numpy.py
medium_multiply_test2-0.1.2.dist-info/METADATA
medium_multiply_test2-0.1.2.dist-info/WHEEL
medium_multiply_test2-0.1.2.dist-info/top_level.txt
medium_multiply_test2-0.1.2.dist-info/RECORD
